awscli_plugin_credential_mfa.py
awscli_plugin_credential_mfa-1.0.1.dist-info/DESCRIPTION.rst
awscli_plugin_credential_mfa-1.0.1.dist-info/METADATA
awscli_plugin_credential_mfa-1.0.1.dist-info/RECORD
awscli_plugin_credential_mfa-1.0.1.dist-info/WHEEL
awscli_plugin_credential_mfa-1.0.1.dist-info/metadata.json
awscli_plugin_credential_mfa-1.0.1.dist-info/top_level.txt
