Metadata-Version: 2.0
Name: awscli-plugin-credential-mfa
Version: 1.0.1
Summary: awscli plugin enabling automatic usage of mfa token
Home-page: https://github.com/seporaitis/awscli-plugin-credential-mfa/
Author: Julius Seporaitis
Author-email: julius@seporaitis.net
License: Apache License 2.0
Keywords: awscli,plugin,credentials,mfa,security,totp,otp,aws
Platform: UNKNOWN
Classifier: Development Status :: 3 - Alpha
Classifier: Intended Audience :: Developers
Classifier: Intended Audience :: System Administrators
Classifier: Natural Language :: English
Classifier: License :: OSI Approved :: Apache Software License
Classifier: Programming Language :: Python
Classifier: Programming Language :: Python :: 2
Classifier: Programming Language :: Python :: 2.7
Classifier: Programming Language :: Python :: 3
Classifier: Programming Language :: Python :: 3.4
Classifier: Programming Language :: Python :: 3.5
Classifier: Programming Language :: Python :: 3.6
Requires-Python: >=2.7, !=3.0.*, !=3.1.*, !=3.2.*, !=3.3.*
Requires-Dist: awscli (>=1.15.81)
